MANIFEST.in
README.rst
buildout.cfg
develop.cfg
requirements.txt
setup.py
version.txt
bob/__init__.py
bob.db.nist_sre12.egg-info/PKG-INFO
bob.db.nist_sre12.egg-info/SOURCES.txt
bob.db.nist_sre12.egg-info/dependency_links.txt
bob.db.nist_sre12.egg-info/entry_points.txt
bob.db.nist_sre12.egg-info/not-zip-safe
bob.db.nist_sre12.egg-info/requires.txt
bob.db.nist_sre12.egg-info/top_level.txt
bob/db/__init__.py
bob/db/nist_sre12/__init__.py
bob/db/nist_sre12/create.py
bob/db/nist_sre12/driver.py
bob/db/nist_sre12/models.py
bob/db/nist_sre12/query.py
bob/db/nist_sre12/test.py
doc/conf.py
doc/guide.rst
doc/index.rst
doc/py_api.rst