Metadata-Version: 1.1
Name: bob.db.nist-sre12
Version: 3.0.4
Summary: Speaker verification protocol on the NIST SRE 2012
Home-page: https://gitlab.idiap.ch/bob/bob.db.nist_sre12
Author: Marc Ferras
Author-email: marc.ferras@idiap.ch
License: GPLv3
Keywords: Spear,Speaker Recognition,Speaker verification,Audio processing,NIST SRE 2012,Database
Platform: UNKNOWN
Classifier: Framework :: Bob
Classifier: Development Status :: 4 - Beta
Classifier: Environment :: Console
Classifier: Intended Audience :: Developers
Classifier: Intended Audience :: Education
Classifier: Intended Audience :: Science/Research
Classifier: License :: OSI Approved :: GNU General Public License v3 (GPLv3)
Classifier: Natural Language :: English
Classifier: Programming Language :: Python
Classifier: Programming Language :: Python :: 3
Classifier: Topic :: Scientific/Engineering :: Artificial Intelligence
Classifier: Topic :: Database :: Front-Ends
